accounting/__init__.py
accounting/commands.py
accounting/forms.py
accounting/locale.py
accounting/models.py
accounting/template_filters.py
accounting/template_globals.py
accounting/account/__init__.py
accounting/account/commands.py
accounting/account/converters.py
accounting/account/forms.py
accounting/account/queries.py
accounting/account/views.py
accounting/base_account/__init__.py
accounting/base_account/commands.py
accounting/base_account/converters.py
accounting/base_account/queries.py
accounting/base_account/views.py
accounting/currency/__init__.py
accounting/currency/commands.py
accounting/currency/converters.py
accounting/currency/forms.py
accounting/currency/queries.py
accounting/currency/views.py
accounting/data/base_accounts.csv
accounting/data/currencies.csv
accounting/journal_entry/__init__.py
accounting/journal_entry/converters.py
accounting/journal_entry/template_filters.py
accounting/journal_entry/views.py
accounting/journal_entry/forms/__init__.py
accounting/journal_entry/forms/currency.py
accounting/journal_entry/forms/journal_entry.py
accounting/journal_entry/forms/line_item.py
accounting/journal_entry/forms/reorder.py
accounting/journal_entry/utils/__init__.py
accounting/journal_entry/utils/account_option.py
accounting/journal_entry/utils/description_editor.py
accounting/journal_entry/utils/operators.py
accounting/journal_entry/utils/original_line_items.py
accounting/option/__init__.py
accounting/option/forms.py
accounting/option/views.py
accounting/report/__init__.py
accounting/report/converters.py
accounting/report/template_filters.py
accounting/report/views.py
accounting/report/period/__init__.py
accounting/report/period/chooser.py
accounting/report/period/description.py
accounting/report/period/month_end.py
accounting/report/period/parser.py
accounting/report/period/period.py
accounting/report/period/shortcuts.py
accounting/report/period/specification.py
accounting/report/reports/__init__.py
accounting/report/reports/balance_sheet.py
mia_accounting-1.6.1.dist-info/LICENSE
mia_accounting-1.6.1.dist-info/METADATA
mia_accounting-1.6.1.dist-info/WHEEL
mia_accounting-1.6.1.dist-info/top_level.txt
mia_accounting-1.6.1.dist-info/RECORD
