Metadata-Version: 2.1
Name: mia-accounting
Version: 1.6.1
Summary: A Flask accounting module.
Author-email: imacat <imacat@mail.imacat.idv.tw>
Project-URL: Documentation, https://mia-accounting.readthedocs.io
Project-URL: Change Log, https://mia-accounting.readthedocs.io/en/latest/changelog.html
Project-URL: Repository, https://github.com/imacat/mia-accounting
Project-URL: Bug Tracker, https://github.com/imacat/mia-accounting/issues
Project-URL: Demonstration, https://accounting.imacat.idv.tw
Keywords: mia,accounting,flask
Classifier: Programming Language :: Python :: 3
Classifier: License :: OSI Approved :: Apache Software License
Classifier: Operating System :: OS Independent
Classifier: Framework :: Flask
Classifier: Topic :: Office/Business :: Financial :: Accounting
Requires-Python: >=3.12
License-File: LICENSE
Requires-Dist: Flask
Requires-Dist: SQLAlchemy>=2
Requires-Dist: Flask-SQLAlchemy
Requires-Dist: Flask-WTF
Requires-Dist: Flask-Babel>=3
Requires-Dist: Flask-Babel-JS
Provides-Extra: devel
Requires-Dist: httpx>=0.20.0; extra == "devel"
Requires-Dist: OpenCC; extra == "devel"
